MANIFEST.in
README.txt
TODO.txt
setup.py
Products/__init__.py
Products.ImageRepository.egg-info/PKG-INFO
Products.ImageRepository.egg-info/SOURCES.txt
Products.ImageRepository.egg-info/dependency_links.txt
Products.ImageRepository.egg-info/namespace_packages.txt
Products.ImageRepository.egg-info/not-zip-safe
Products.ImageRepository.egg-info/requires.txt
Products.ImageRepository.egg-info/top_level.txt
Products/ImageRepository/__init__.py
Products/ImageRepository/config.py
Products/ImageRepository/configure.zcml
Products/ImageRepository/field.py
Products/ImageRepository/interfaces.py
Products/ImageRepository/permissions.py
Products/ImageRepository/setuphandlers.py
Products/ImageRepository/version.txt
Products/ImageRepository/widget.py
Products/ImageRepository/browser/__init__.py
Products/ImageRepository/browser/configure.zcml
Products/ImageRepository/browser/imagerepository.py
Products/ImageRepository/browser/thumbnail.py
Products/ImageRepository/content/ImageRepository.py
Products/ImageRepository/content/__init__.py
Products/ImageRepository/i18n/ImageRepository-plone-de.po
Products/ImageRepository/i18n/ImageRepository-plone-manual.pot
Products/ImageRepository/i18n/ImageRepository-plone-no.po
Products/ImageRepository/i18n/ImageRepository-plone-pt-br.po
Products/ImageRepository/i18n/ImageRepository-plone-ru.po
Products/ImageRepository/i18n/ImageRepository-plone.pot
Products/ImageRepository/i18n/update.sh
Products/ImageRepository/profiles/default/imagerepository_kupu.txt
Products/ImageRepository/profiles/default/import_steps.xml
Products/ImageRepository/profiles/default/metadata.xml
Products/ImageRepository/profiles/default/propertiestool.xml
Products/ImageRepository/profiles/default/skins.xml
Products/ImageRepository/profiles/default/types.xml
Products/ImageRepository/profiles/default/types/ImageRepository.xml
Products/ImageRepository/resources/select_all.js
Products/ImageRepository/skins/ImageRepository/imagerepository_addKeywords.cpy
Products/ImageRepository/skins/ImageRepository/imagerepository_addKeywords.cpy.metadata
Products/ImageRepository/skins/ImageRepository/imagerepository_collection.xml.pt
Products/ImageRepository/skins/ImageRepository/imagerepository_collection.xml.pt.metadata
Products/ImageRepository/skins/ImageRepository/imagerepository_collectionInfos.py
