Metadata-Version: 1.0
Name: Products.ImageRepository
Version: 0.9
Summary: A centralized image repository with keyword/tag-based browsing and filtering.
Home-page: http://plone.org/products/imagerepository
Author: Jarn AS
Author-email: info@jarn.com
License: GPL
Keywords: plone images repository centralized keywords
Platform: Any
Classifier: Environment :: Web Environment
Classifier: Framework :: Plone
Classifier: Intended Audience :: Developers
Classifier: License :: OSI Approved :: GNU General Public License (GPL)
Classifier: Operating System :: OS Independent
Classifier: Programming Language :: Python
